quickstartup/__init__.py
quickstartup/context_processors.py
quickstartup/settings_utils.py
quickstartup/template_loader.py
quickstartup/urls.py
quickstartup/qs_accounts/__init__.py
quickstartup/qs_accounts/admin.py
quickstartup/qs_accounts/apps.py
quickstartup/qs_accounts/forms.py
quickstartup/qs_accounts/models.py
quickstartup/qs_accounts/signals.py
quickstartup/qs_accounts/urls.py
quickstartup/qs_accounts/views.py
quickstartup/qs_accounts/locale/pt_BR/LC_MESSAGES/django.mo
quickstartup/qs_accounts/locale/pt_BR/LC_MESSAGES/django.po
quickstartup/qs_accounts/migrations/0001_initial.py
quickstartup/qs_accounts/migrations/0002_add_new_permission_fields_to_user.py
quickstartup/qs_accounts/migrations/__init__.py
quickstartup/qs_accounts/templates/_accounts/accounts.html
quickstartup/qs_accounts/templates/_accounts/activation-error.html
quickstartup/qs_accounts/templates/_accounts/base-profile.html
quickstartup/qs_accounts/templates/_accounts/email-change.html
quickstartup/qs_accounts/templates/_accounts/password-change.html
quickstartup/qs_accounts/templates/_accounts/profile.html
quickstartup/qs_accounts/templates/_accounts/reset-confirm.html
quickstartup/qs_accounts/templates/_accounts/reset.html
quickstartup/qs_accounts/templates/_accounts/signin.html
quickstartup/qs_accounts/templates/_accounts/signup-closed.html
quickstartup/qs_accounts/templates/_accounts/signup-complete.html
quickstartup/qs_accounts/templates/_accounts/signup.html
quickstartup/qs_accounts/templates/_emails/activation-body-html.html
quickstartup/qs_accounts/templates/_emails/activation-body-text.html
quickstartup/qs_accounts/templates/_emails/activation-subject.html
quickstartup/qs_accounts/templates/_emails/change_email-body-html.html
quickstartup/qs_accounts/templates/_emails/change_email-body-text.html
quickstartup/qs_accounts/templates/_emails/change_email-subject.html
quickstartup/qs_accounts/templates/_emails/password_reset-body-html.html
quickstartup-0.19.0.dist-info/LICENSE.txt
quickstartup-0.19.0.dist-info/METADATA
quickstartup-0.19.0.dist-info/WHEEL
quickstartup-0.19.0.dist-info/top_level.txt
quickstartup-0.19.0.dist-info/RECORD
