Metadata-Version: 2.1
Name: quickstartup
Version: 0.19.0
Summary: Quickstartup package used by Quickstartup Template
Home-page: https://github.com/osantana/quickstartup
Author: Osvaldo Santana Neto
Author-email: quickstartup@osantana.me
License: MIT
Keywords: quickstartup
Platform: UNKNOWN
Classifier: Development Status :: 2 - Pre-Alpha
Classifier: Framework :: Django
Classifier: Intended Audience :: Developers
Classifier: License :: OSI Approved :: MIT License
Classifier: Natural Language :: English
Classifier: Programming Language :: Python :: 3
Classifier: Programming Language :: Python :: 3.7
Requires-Dist: django (<3.2,>=3.1)
Requires-Dist: django-widget-tweaks (<1.5,>=1.4)
Requires-Dist: django-model-utils (<4.1,>=4.0)
Requires-Dist: django-ipware (<3.1,>=3.0)
Requires-Dist: djmail (<2.1,>=2.0)
